dj_split_settings/__init__.py
dj_split_settings/utils/__init__.py
dj_split_settings/utils/collections.py
dj_split_settings/utils/misc.py
dj_split_settings/utils/settings.py
dj_split_settings-0.1.3.dist-info/LICENSE
dj_split_settings-0.1.3.dist-info/METADATA
dj_split_settings-0.1.3.dist-info/WHEEL
dj_split_settings-0.1.3.dist-info/RECORD
