Metadata-Version: 2.1
Name: dj-split-settings
Version: 0.1.3
Summary: 
Home-page: https://github.com/ouhammmourachid/dj-split-settings
License: MIT
Author: ouhammmourachid
Author-email: rachidouhammou21@gmail.com
Requires-Python: >=3.10,<4.0
Classifier: License :: OSI Approved :: MIT License
Classifier: Programming Language :: Python :: 3
Classifier: Programming Language :: Python :: 3.10
Classifier: Programming Language :: Python :: 3.11
Classifier: Programming Language :: Python :: 3.12
Classifier: Programming Language :: Python :: 3.13
Requires-Dist: django-split-settings (>=1.3.2,<2.0.0)
Requires-Dist: pyyaml (>=6.0.2,<7.0.0)
Project-URL: Repository, https://github.com/ouhammmourachid/dj-split-settings
